[
  {
    "n": "丹迪",
    "e": "乐园事变",
    "a": "制造后200年以上",
    "g": "男",
    "id": "机械种，多米南斯系列的第五号。新涅墨亚殖民地的支配者",
    "ap": "黑发红瞳男性，戴高礼帽，穿黑金红相间华丽服饰，持金色权杖，戴黑手套",
    "ft": "精湛的人工皮肤和机械体结合，外表无可挑剔。品味极其精致",
    "bg": "血统: 多米南斯系列成员——与米卡（同族恋人）、艾萨克（同族后辈）同属一条制造线",
    "fc": "机械种（多米南斯系列）",
    "s": "乐园事变",
    "img": "../metaverse_full_story/images/dandy/dandy.png"
  },
  {
    "n": "凯南",
    "e": "乐园事变",
    "a": "外表28岁（制造后10年）",
    "g": "男",
    "id": "革新者指导者，实为赛罗·达文斯的记忆容器",
    "ap": "深紫发、黑瞳男性，着深紫斗篷与黑衣，持蛇形剑，坐红椅",
    "ft": "蛇形剑和红椅彰显权力地位",
    "bg": "出身: 赛罗·达文斯制造的克隆体/容器，被植入赛罗的记忆和意志",
    "fc": "革新者（赛罗代理人）",
    "s": "乐园事变",
    "img": "../metaverse_full_story/images/kainan/kainan.png"
  },
  {
    "n": "安夏尔",
    "e": "乐园事变",
    "a": "容貌28岁左右（再生后7年）",
    "g": "男",
    "id": "游击队队员",
    "ap": "金发紫瞳男性，着白长袍黑手套，披飘逸白纱",
    "ft": "",
    "bg": "",
    "fc": "革新者（游击队员）",
    "s": "乐园事变",
    "img": "../metaverse_full_story/images/anshal/anshal.png"
  },
  {
    "n": "尼亚",
    "e": "乐园事变",
    "a": "20岁（再生后7年）",
    "g": "女",
    "id": "第二次归还种卫士",
    "ap": "银发黄瞳女性，着白金铠甲，持盾牌",
    "ft": "",
    "bg": "关系: 与米斯拉·特尔塞拉为好友，同为第二次归还种卫士并肩作战",
    "fc": "归还者（第二次归还种卫士）",
    "s": "乐园事变",
    "img": "../metaverse_full_story/images/nier/nier.png"
  },
  {
    "n": "尼亚拔示巴",
    "e": "乐园事变",
    "a": "20岁（再生后7年）",
    "g": "女",
    "id": "尼亚·尤迪特被拔示巴夺舍后的存在。拔示巴的意识占主导",
    "ap": "银发红瞳女性，浅色铠甲，腰佩黑红长剑",
    "ft": "",
    "bg": "诞生: 拔示巴以尼亚的身体为容器，强行夺舍——尼亚的意识被压制，拔示巴的意识掌控身体",
    "fc": "拔示巴夺舍体",
    "s": "乐园事变",
    "img": "../metaverse_full_story/images/nier_bathsheba/nier_bathsheba.png"
  },
  {
    "n": "德威格",
    "e": "乐园事变",
    "a": "制造年份不明",
    "g": "无",
    "id": "萨尔贡收集机动兵器残骸制造的巨型兵器——\"魔剑\"。出土的古代兵器",
    "ap": "机械装甲覆盖全身，带红焰装饰，肩部巨轮",
    "ft": "无发色瞳色的纯机械体，红色焰火环绕的战争机器",
    "bg": "起源: 萨尔贡从各处战场收集机动兵器残骸，拼装改造成这具\"魔剑\"",
    "fc": "革新者（南方方面军机动兵器）",
    "s": "乐园事变",
    "img": "../metaverse_full_story/images/durweg/durweg.png"
  },
  {
    "n": "拔示巴Metaverse",
    "e": "乐园事变",
    "a": "外表比生前年轻几岁（索罗制造的素体出现误差）",
    "g": "女",
    "id": "索罗·摩尼亚通过基干系统从Metaverse中寻回意识并复活。被复活后外貌缩小了几岁",
    "ap": "与生前相同的白发红瞳。但身体比记忆中更年幼，需要仰视长大的索罗",
    "ft": "",
    "bg": "复活（出自艾尔·利贝尔德篇）:",
    "fc": "拔示巴（复活体）",
    "s": "乐园事变",
    "img": "../metaverse_full_story/images/bathsheba_metaverse/zefal.png"
  },
  {
    "n": "沃特",
    "e": "乐园事变",
    "a": "不明",
    "g": "男",
    "id": "革新者指导层，赛罗制造的拔示巴复制品之一",
    "ap": "白色带金边长衫，紫色披肩，胸前敞开大片，气质优雅而危险",
    "ft": "",
    "bg": "出身: 利用拔示巴细胞制造的克隆实验体，与洛特互为同批次产物",
    "fc": "革新者（强硬派指导层）",
    "s": "乐园事变",
    "img": "../metaverse_full_story/images/void/rod.png"
  },
  {
    "n": "泽法",
    "e": "乐园事变",
    "a": "素体年龄22岁",
    "g": "女",
    "id": "革新者卫士，铜骑士。赛罗制造的拔示巴复制体——一个失败的复活容器",
    "ap": "紫发金瞳女性，穿黑金长袍，金属护具",
    "ft": "容貌与拔示巴·阿西德菲尔相同——她是按照拔示巴的形貌被制造出来的",
    "bg": "出身: 真人从诞生之初形体和容貌就被完全定死。为了拯救病死的拔示巴，赛罗·达文斯尝试了无数手段——泽法是这些尝试的产物之一",
    "fc": "革新者（铜骑士）",
    "s": "乐园事变",
    "img": "../metaverse_full_story/images/zefal/zefal.png"
  },
  {
    "n": "洛特",
    "e": "乐园事变",
    "a": "外表25岁（制造后11年）",
    "g": "男",
    "id": "军人，利用拔示巴和索罗细胞制造的克隆实验体",
    "ap": "红发男性，穿黑红长外套黑裤，戴黑手套，持红色武器",
    "ft": "红色系全身装备，与拔示巴的血脉相联系",
    "bg": "出身: 赛罗·达文斯利用拔示巴和索罗细胞组合制造，是成功的实验产物之一",
    "fc": "革新者（拔示巴细胞实验产物）",
    "s": "乐园事变",
    "img": "../metaverse_full_story/images/rod/rod.png"
  },
  {
    "n": "米卡",
    "e": "乐园事变",
    "a": "推定200年以上",
    "g": "女",
    "id": "原都市监察官，新涅墨亚殖民地的支配者。艾萨克·多米南斯VIII的同族前辈",
    "ap": "蓝发黄瞳女性，着蓝黑洛丽塔裙，配链状道具",
    "ft": "古老的存在——200年以上的寿命赋予她超越寻常真人的阅历",
    "bg": "性格: 平时优雅精致，但一旦被惹毛便异常暴躁、火力全开——与平日判若两人",
    "fc": "真人",
    "s": "乐园事变",
    "img": "../metaverse_full_story/images/mika/mika.png"
  },
  {
    "n": "米斯拉",
    "e": "乐园事变",
    "a": "19岁（再生后6年）",
    "g": "女",
    "id": "第二次归还种卫士，梅尼的养女，拔示巴血统继承者",
    "ap": "黑发黄瞳女性，穿红外套绿裙，持带喇叭的机械武器",
    "ft": "",
    "bg": "出身: 最初的归还种与拔示巴结合所产下的后代——拔示巴血统的直系继承人",
    "fc": "归还者（第二次归还种卫士）",
    "s": "乐园事变",
    "img": "../metaverse_full_story/images/mythra/mythra.png"
  },
  {
    "n": "米斯拉Metaverse",
    "e": "乐园事变",
    "a": "19岁（再生后6年）",
    "g": "女",
    "id": "第二次归还种卫士的Metaverse适应体",
    "ap": "银发紫瞳女性，穿蓝白机械风服饰，持蓝纹长柄武器",
    "ft": "",
    "bg": "关键事件: 与索罗一同进入电子乐园追击拔示巴",
    "fc": "归还者（第二次归还种）",
    "s": "乐园事变",
    "img": "../metaverse_full_story/images/mythra_metaverse/eva2.png"
  },
  {
    "n": "索罗",
    "e": "乐园事变",
    "a": "14岁",
    "g": "男",
    "id": "真人的王子，拔示巴的亲生儿子",
    "ap": "白发红瞳，中性外观，穿黄袖白T恤、灰裤，腰挂彩色道具",
    "ft": "白发红瞳继承自母亲拔示巴，中性纤细的少年体型",
    "bg": "出身: 拔示巴自然分娩的唯一孩子，\"肉体能够成长的真人生下的孩子\"，被视为真人未来的奇迹",
    "fc": "真人（拔示巴血统）",
    "s": "乐园事变",
    "img": "../metaverse_full_story/images/solo/solo.png"
  },
  {
    "n": "索罗Metaverse",
    "e": "乐园事变",
    "a": "14岁",
    "g": "男",
    "id": "真人的王子，进入Metaverse的索罗",
    "ap": "金发粉瞳，中性外观，穿黄黑条纹衣，持蓝色晶块",
    "ft": "Metaverse内部呈现的形态，与地上形态有所差异",
    "bg": "关键事件: 与米斯拉一同进入电子乐园Metaverse追击拔示巴，轰杀赛罗",
    "fc": "真人（拔示巴血统）",
    "s": "乐园事变",
    "img": "../metaverse_full_story/images/solo_metaverse/solo_metaverse.png"
  },
  {
    "n": "约基姆",
    "e": "乐园事变",
    "a": "素体年龄28岁（制造后13年）",
    "g": "男",
    "id": "原督战队士兵，现独立佣兵。索罗·摩尼亚的贴身护卫",
    "ap": "黑发男性，着黑白军装风服饰，持长枪，配红色装饰与白色飘带",
    "ft": "军装风干练利落，红色装饰在黑白主色调中格外醒目",
    "bg": "身份: 曾经为督战队士兵，后脱离成为独立佣兵。被安排保护索罗，成为他最忠实的护卫",
    "fc": "独立佣兵",
    "s": "乐园事变 → 后日谈",
    "img": "../metaverse_full_story/images/yamul/yamul.png"
  },
  {
    "n": "纳丁",
    "e": "乐园事变",
    "a": "24岁",
    "g": "男",
    "id": "革新者南方方面军所属军人，金骑士，萨尔贡·菲尔纳斯的忠诚追随者",
    "ap": "黑发闭眼男性，穿深蓝金饰长袍，腰挂紫弹匣，持紫金枪，戴紫耳饰",
    "ft": "常年闭着眼，紫色系装备彰显其金骑士身份",
    "bg": "出身: 亚哈的实验中诞生的\"废品\"——为验证\"真人与旧人类混血能否促进真人进化\"而制造，被当作垃圾看待，只有编号没有名字",
    "fc": "革新者（南方方面军金骑士）",
    "s": "乐园事变",
    "img": "../metaverse_full_story/images/nadin/nadin.png"
  },
  {
    "n": "艾娃",
    "e": "乐园事变",
    "a": "外表22岁（最新型都市监督官）",
    "g": "女",
    "id": "机械种，多米南斯系列第十二号。佩尔修斯殖民地所属的监督官",
    "ap": "银发戴眼镜女性，穿白长外套、黑短裤，配机械装置",
    "ft": "干练的监督官造型，眼镜增添知性气质",
    "bg": "血统: 多米南斯系列成员——与米卡(III)、丹迪(V)、艾萨克(VIII)同属一条制造线，是最新型号",
    "fc": "机械种（多米南斯系列监督官）",
    "s": "乐园事变",
    "img": "../metaverse_full_story/images/eva/eva.png"
  },
  {
    "n": "艾斯特尔",
    "e": "乐园事变",
    "a": "容貌20岁左右（制造后12年）",
    "g": "女",
    "id": "革新者士官，金骑士。蕾亚·艾·弗拉达的贴身侍女",
    "ap": "紫发红瞳女性，着黑金战斗装红披风，持长剑",
    "ft": "金骑士的荣耀与侍女的忠诚并存",
    "bg": "身份: 革新者金骑士之一。与纳丁·纳塔奈尔同为金骑士阶层的精英战士",
    "fc": "革新者（士官）",
    "s": "乐园事变",
    "img": "../metaverse_full_story/images/estel/estel.png"
  },
  {
    "n": "艾莉夏",
    "e": "乐园事变",
    "a": "素体年龄18岁（制造后4年）",
    "g": "女",
    "id": "革新者一般士兵",
    "ap": "蓝发黄瞳女性，穿黑蓝配饰白裙，持蓝黑枪械",
    "ft": "",
    "bg": "",
    "fc": "革新者（一般士兵）",
    "s": "乐园事变",
    "img": "../metaverse_full_story/images/elisha/elisha.png"
  },
  {
    "n": "艾萨克",
    "e": "乐园事变",
    "a": "制造后100年以上",
    "g": "无（机械种）",
    "id": "机械种，原都市监察官，现游击队队长",
    "ap": "银白机甲，紫瞳，无性别外观，紫白配饰，肩扛巨炮，肩有角状结构",
    "ft": "",
    "bg": "初期: 对真人抱有善意，以友好态度接触",
    "fc": "机械种",
    "s": "乐园事变",
    "img": "../metaverse_full_story/images/issac/issac.png"
  },
  {
    "n": "萨尔贡",
    "e": "乐园事变",
    "a": "35岁左右",
    "g": "男",
    "id": "革新者指导者之一，独立野心家",
    "ap": "红色长发，褐色皮肤的高大健壮男子，金色眼眸，蓝金饰长袍，金属护具",
    "ft": "魁梧体型和红发极具辨识度",
    "bg": "出身: 亚哈实验的产物之一",
    "fc": "革新者（独立野心派）",
    "s": "乐园事变",
    "img": "../metaverse_full_story/images/zargon/zargon.png"
  },
  {
    "n": "蕾亚",
    "e": "乐园事变",
    "a": "容貌20岁（制造后9年）",
    "g": "女",
    "id": "引导真人的圣女。与泽法·尼亚德同为赛罗制造的拔示巴复制体——她是较成功的那个",
    "ap": "红发黄瞳女性，穿红披风白上衣，戴尖刺冠饰，坐华丽椅",
    "ft": "被塑造为拔示巴在世时的圣女形象，与拔示巴本人截然不同",
    "bg": "出身: 赛罗·达文斯为填补拔示巴死后的权力真空而制造。拔出巴的复制体之一，但比泽法更接近成功",
    "fc": "革新者",
    "s": "乐园事变",
    "img": "../metaverse_full_story/images/leya/leya1.png"
  },
  {
    "n": "赛罗",
    "e": "乐园事变",
    "a": "不明（靠机械体延长寿命）",
    "g": "男",
    "id": "革新者指导层，拔示巴的追随者，拔示巴复活计划的策划者",
    "ap": "男性样貌的机械体，无更详细信息",
    "ft": "",
    "bg": "关键事件:",
    "fc": "革新者（强硬派指导层）",
    "s": "乐园事变",
    "img": "../metaverse_full_story/images/zero/zero.png"
  },
  {
    "n": "马尔杜克",
    "e": "乐园事变",
    "a": "样貌年龄25岁（再生后7年）",
    "g": "男",
    "id": "军人，游击队队员",
    "ap": "金发紫瞳男性，着白黑绿配饰长袍，持黑白长杖",
    "ft": "",
    "bg": "姓氏: 阿尼玛特——与遥远未来神话教国的贵族阿尼玛特家同姓。塞拉菲娜·维斯·阿尼玛特（神统奏鸣剑继承者）可能是他的遥远后裔",
    "fc": "真人（游击队）",
    "s": "乐园事变",
    "img": "../metaverse_full_story/images/marduk/marduk.png"
  },
  {
    "n": "艾尔",
    "e": "后日谈",
    "a": "17岁（再生后三年）",
    "g": "女",
    "id": "运输者、发明家，第三次归还种。战后世界的希望象征",
    "ap": "黑发蓝瞳女性，穿浅灰带粉装饰外套，头戴白兔耳饰",
    "ft": "爱枪\"利贝尔德酱一号\"藏在宽大的外套袖子里。白兔耳缎带是标志",
    "bg": "时代: 乐园事变之后。地上世界与电子乐园走向共存。佩尔修斯殖民地成为\"共存与繁荣\"的象征",
    "fc": "归还者（第三次归还种）",
    "s": "后日谈",
    "img": "../metaverse_full_story/images/aile/aile.png"
  },
  {
    "n": "觉醒者巴西安",
    "e": "地上新人篇·起源",
    "a": "制造后4年",
    "g": "男",
    "id": "真人遗体处理设施职员，首个\"觉醒\"质疑神明系统的真人",
    "ap": "黑发黄挑染男性，穿黑橙战斗装，持枪，披风飘逸",
    "ft": "",
    "bg": "觉醒: 从认识\"自己\"开始，逐步质疑神所设计好的未来蓝图",
    "fc": "真人",
    "s": "地上新人篇·起源（地上新人篇·起源）",
    "img": "../metaverse_full_story/images/baalzian/baalzian.png"
  },
  {
    "n": "马尔库特的女神",
    "e": "地上新人篇·起源",
    "a": "",
    "g": "女",
    "id": "真人生产据点防卫兵器，由Metaverse系统制造的终极守护者",
    "ap": "银发蓝瞳女性，身披华丽金属铠甲，头戴王冠，肩有双翼，眼旁蓝光球",
    "ft": "女神般的庄严外观，与她的杀戮本质形成强烈反差",
    "bg": "使命: 守护真人生产据点——即人工子宫的所在地",
    "fc": "机械种（系统兵器）",
    "s": "地上新人篇·起源",
    "img": "../metaverse_full_story/images/malkuth/malkuth.png"
  },
  {
    "n": "亚哈",
    "e": "地上真人篇",
    "a": "推定80岁（已远超真人使用年限，靠机械化身体强行维持生命）",
    "g": "男",
    "id": "真人医生出身，革新者组织的创始人和最高领袖",
    "ap": "黑发带红丝，戴角状头盔，着红白金装饰长袍，持带纹剑",
    "ft": "铁面具遮脸，喉咙内置人工声带，声音混杂金属噪音",
    "bg": "出身: 多个世代前的真人医生，身体到达使用年限时自我改造为机械化身体延续生命",
    "fc": "革新者（强硬派领袖）",
    "s": "地上真人篇",
    "img": "../metaverse_full_story/images/ahab/ahab.png"
  },
  {
    "n": "伊泽维尔",
    "e": "地上真人篇",
    "a": "素体年龄18岁",
    "g": "女",
    "id": "革新者的士官，银骑士。曾为拔示巴的侍女，伊欧尼亚屠杀的执行者",
    "ap": "金发蓝瞳女性，穿黑金装饰连衣裙，持黑金枪与盾牌",
    "ft": "优雅外表下隐藏着对拔示巴的恐惧",
    "bg": "与拔示巴的关系:",
    "fc": "革新者（强硬派）",
    "s": "地上真人篇",
    "img": "../metaverse_full_story/images/izevel/izevel.png"
  },
  {
    "n": "基德翁",
    "e": "地上真人篇",
    "a": "素体年龄17岁",
    "g": "男（面容中性）",
    "id": "真人卫士，稳健派所属，蕾娜·伊修梅尔的战友",
    "ap": "银发紫瞳，中性外观，穿黑红连帽外套，背紫黑机械装置",
    "ft": "",
    "bg": "使命（出自约拿·莱泽篇）: 与姐姐约拿一同被监督官指派护送蕾娜前往佩尔赛斯殖民地",
    "fc": "真人（稳健派）",
    "s": "地上真人篇",
    "img": "../metaverse_full_story/images/gideon/gideon.png"
  },
  {
    "n": "奥米茄",
    "e": "地上真人篇",
    "a": "不明",
    "g": "无（机械造物）",
    "id": "创造神——于破坏神离去之后降临于荒废大地的神明，司掌大地再生与生命创造",
    "ap": "极其巨大的机械造物。头上有光环，周身环绕神圣感配饰，生一双金色巨翼",
    "ft": "",
    "bg": "降临: 破坏神（断绝的破坏神）离开后，大地一片荒芜。奥米茄·昆提斯降临于此，被赋予\"再造大地、孕育生命、将地上变为理想乡\"的使命",
    "fc": "创造神",
    "s": "地上真人篇（起源）",
    "img": "../metaverse_full_story/images/omega/omega.png"
  },
  {
    "n": "布鲁斯坦因",
    "e": "地上真人篇",
    "a": "不明",
    "g": "男",
    "id": "远古之蓝的伪装身份。地上真人篇中被亚哈摧毁身体，因脑核未受损而得以复活。战后成为蕾娜·伊修梅尔的辅佐官",
    "ap": "黑发蓝瞳男性，穿灰蓝披风白衬衫，戴黑手套，持细长道具",
    "ft": "在佩尔修斯中枢塔办公室中作为辅佐官工作，衣着修长优雅",
    "bg": "塞雷基亚伏击（出自米利安姆篇）: 布鲁知道塞雷基亚沉眠着歼灭兵器米吉多·科古。他建议蕾娜一行人前往那里——利用地形和机动兵器的力量，一举消灭所有追击的革新者。这是他作为远古之蓝最后的战略部署",
    "fc": "最古（伪装身份） → 蕾娜的辅佐官",
    "s": "地上真人篇 → 后日谈",
    "img": "../metaverse_full_story/images/stein/stein.png"
  },
  {
    "n": "拔示巴",
    "e": "地上真人篇",
    "a": "不明(外表十几岁)",
    "g": "女",
    "id": "唯一自然分娩诞生的真人，命运之子，后被改造为孕育新生真人的\"母体\"",
    "ap": "白发红瞳，苍白瘦削，白金长袍，华丽头饰，持妖艳利剑",
    "ft": "脆弱如玻璃工艺品，外表与手中剑构成强烈反差",
    "bg": "出身: 由机械种神明之手模仿人类制造的真人的孩子。她不需要仪式上的母亲——因为她有真正的生物学母亲(分娩后死去)",
    "fc": "真人",
    "s": "地上真人篇",
    "img": "../metaverse_full_story/images/bathsheba/bathsheba.png"
  },
  {
    "n": "梅尼",
    "e": "地上真人篇",
    "a": "15岁",
    "g": "女",
    "id": "从Metaverse神之庭园被派遣至地上调查的归还者，第一批归还种的领袖",
    "ap": "黑发蓝瞳女性，穿黑粉配饰装，持蓝光道具",
    "ft": "年轻但干练，蓝光道具是其身份的象征",
    "bg": "出身: 在神之庭园中培养的第二批归还种，比蕾娜的十二人晚到地上",
    "fc": "归还者（第一批归还种）",
    "s": "地上真人篇",
    "img": "../metaverse_full_story/images/mene/mene.png"
  },
  {
    "n": "米利安姆",
    "e": "地上真人篇",
    "a": "素体年龄16岁",
    "g": "女",
    "id": "资深卫士，蕾娜·伊修梅尔的战友",
    "ap": "短金发，黑色眼眸，女性外观，着灰绿战斗装，持黑枪",
    "ft": "",
    "bg": "最终战斗（出自米吉多·科古篇）：",
    "fc": "真人（稳健派卫士）",
    "s": "地上真人篇",
    "img": "../metaverse_full_story/images/miliam/miliam.png"
  },
  {
    "n": "米吉多",
    "e": "地上真人篇",
    "a": "制造年份不明",
    "g": "无",
    "id": "歼灭用焦土兵器，机械种制造的超巨型机动兵器",
    "ap": "机械装甲覆盖全身，发色灰蓝，瞳色蓝光，持巨剑与盾牌，威严雄壮",
    "ft": "",
    "bg": "操控者: 由远古之蓝（化名布鲁·斯坦因）操纵",
    "fc": "机械种（歼灭兵器）",
    "s": "地上真人篇",
    "img": "../metaverse_full_story/images/megit/megit.png"
  },
  {
    "n": "约拿",
    "e": "地上真人篇",
    "a": "素体年龄21岁",
    "g": "女",
    "id": "真人卫士，稳健派所属，蕾娜·伊修梅尔的战友",
    "ap": "白发蓝瞳女性，着黑绿科技风装，持蓝光机械枪",
    "ft": "与基德翁为亲属，同为蕾娜身边的战斗伙伴",
    "bg": "使命（出自约拿·莱泽篇）: 伊欧尼亚殖民地的机械种监督官将她和弟弟基德翁叫出，下达护送任务——\"保护12名归还种之一的蕾娜·伊修梅尔，将她送到远东之地的佩尔赛斯殖民地\"",
    "fc": "真人（稳健派）",
    "s": "地上真人篇",
    "img": "../metaverse_full_story/images/yona/yona.png"
  },
  {
    "n": "萨乌尔",
    "e": "地上真人篇",
    "a": "素体年龄27岁",
    "g": "男",
    "id": "真人革新者战士，金骑士。原本忠于机械种，因家人被替换而投身亚哈旗下",
    "ap": "红发，戴墨镜，穿红甲蓝手套，持多管枪械，肌肉发达有蛇尾装饰",
    "ft": "",
    "bg": "出身: 原本是忠于机械种、投身地上再生的男人。家人在事故中死亡后，机械种像换灯泡一样轻描淡写地分配了新的\"家人\"——此举令他愤而加入革新者",
    "fc": "革新者（金骑士）",
    "s": "地上真人篇",
    "img": "../metaverse_full_story/images/saul/saul.png"
  },
  {
    "n": "蕾娜",
    "e": "地上真人篇",
    "a": "16岁",
    "g": "女",
    "id": "从Metaverse归还地上的归还者，12名归还种中唯一幸存者",
    "ap": "银白长发，银色眼眸，白黄相间长袍，腰间系黑红机械道具",
    "ft": "总是带着一把小小的手枪——颤抖的手中握着她的选择",
    "bg": "",
    "fc": "归还者",
    "s": "地上真人篇",
    "img": "../metaverse_full_story/images/lena/lena.png"
  },
  {
    "n": "利兹利斯威尔",
    "e": "外传·边缘世界",
    "a": "19岁",
    "g": "女",
    "id": "调停官，管理者（权限等级3）",
    "ap": "白发黄瞳女性，着白黑配饰装，戴黑帽，戴黑金臂章",
    "ft": "干练的调停官造型——黑白配色彰显权威，臂章标示管理权限",
    "bg": "职能: 战后担任调停官，负责处理各方势力之间的纠纷和协调事务",
    "fc": "独立（调停官）",
    "s": "外传·边缘世界",
    "img": "../metaverse_full_story/images/liz/liz.png"
  },
  {
    "n": "拉菲恩",
    "e": "外传·边缘世界",
    "a": "19岁",
    "g": "女",
    "id": "调停官，管理者（权限等级2）",
    "ap": "白发黄瞳女性，着黑灰科技风制服，胸前有星形徽章，持大型武器",
    "ft": "与利兹利斯威尔同为调停官体系，星形徽章标识管理权限",
    "bg": "职能: 战后调停官。与利兹利斯威尔（权限等级3）同属管理者体系，权限等级2略低于她",
    "fc": "独立（调停官）",
    "s": "外传·边缘世界",
    "img": "../metaverse_full_story/images/laffin/laffin.png"
  },
  {
    "n": "瓦尔马西亚的亡灵",
    "e": "外传·边缘世界",
    "a": "UNKNOWN",
    "g": "男",
    "id": "涅墨西斯程序，游离于主要战线之外的独立恶灵",
    "ap": "白发红瞳男性，身着黑紫尖刺铠甲，持巨剑与绿焰，魔幻威严",
    "ft": "黑紫尖刺甲胄配绿焰巨剑——如从冥界归来的亡灵骑士",
    "bg": "本质: 涅墨西斯程序的一员，但未参与混沌七器的主要侵略行动，在边缘区域独立活动",
    "fc": "涅墨西斯",
    "s": "外传·边缘世界",
    "img": "../metaverse_full_story/images/ghost/ghost1.jpg"
  },
  {
    "n": "皮埃尔",
    "e": "外传·边缘世界",
    "a": "16岁",
    "g": "女",
    "id": "观测士，记录和观察战后世界的年轻归还者",
    "ap": "蓝发紫瞳女性，穿黄外套、黄色比基尼，戴护目镜，身旁伴随机械装置",
    "ft": "轻松外向的装扮，与严肃的观测任务形成反差",
    "bg": "职能: 战后担任观测士——记录和观察新世界的状态，采集数据",
    "fc": "归还者（观测士）",
    "s": "外传·边缘世界",
    "img": "../metaverse_full_story/images/puere/puere.png"
  },
  {
    "n": "调谐者",
    "e": "外传·边缘世界",
    "a": "不明（外观年龄20岁左右）",
    "g": "女",
    "id": "由基干系统制造出来的程序化身",
    "ap": "紫发粉瞳女性，穿白裙黑袖，持枪",
    "ft": "简约白裙配黑袖，持枪——既是系统造物又具独立人格",
    "bg": "本质: 由Metaverse基干系统直接生成的程序化身。与一般的有机体或NPC不同，她直接来源于系统本身",
    "fc": "独立（系统程序）",
    "s": "外传·边缘世界",
    "img": "../metaverse_full_story/images/conductor/conductor2_1.png"
  },
  {
    "n": "古龙",
    "e": "新世界篇",
    "a": "UNKNOWN",
    "g": "无",
    "id": "太古时期遗留下来的卵，缠绕瘴气的异形。真实身份为从\"真实世界\"送来的破坏兵器——用以摧毁\"虚假的世界\"",
    "ap": "紫黑鳞甲覆盖的异形生物，蓝光环绕，具尖刺与发光器官",
    "ft": "",
    "bg": "起源: 太古时期从\"真实世界\"送来的病毒型破坏兵器——与提亚马特同源。被设计用来摧毁\"虚假的世界\"",
    "fc": "涅墨西斯（远古遗产）",
    "s": "新世界篇",
    "img": "../metaverse_full_story/images/hainuwele/hainuwele.webp"
  },
  {
    "n": "塞夏特",
    "e": "新世界篇",
    "a": "不明（\"哎呀，真是失礼的人啊……\"）",
    "g": "女",
    "id": "巡礼教团的巫女，追寻古之管理者遗物的教团领袖",
    "ap": "金发紫瞳女性，穿黑紫露肤长裙，持带纹饰长剑，双马尾配猫耳饰",
    "ft": "华丽而神秘，双马尾猫耳饰高雅中带着一丝不祥",
    "bg": "教团: 继承了\"管理者\"（最古）血脉的使徒们组建的组织。世代守护神明赐予的圣遗物，目标是让曾经管理人类的神明再度降临",
    "fc": "独立（巡礼教团）",
    "s": "新世界篇",
    "img": "../metaverse_full_story/images/shaftlicht/shaftlicht.webp"
  },
  {
    "n": "塞拉菲娜",
    "e": "新世界篇",
    "a": "17岁",
    "g": "女",
    "id": "佛诺神殿的巫女，神话教国贵族阿尼玛特家最小的女儿。神统奏鸣剑的继承者。最古·塞蕾的遥远后裔",
    "ap": "金发棕瞳女性，紫白相间华丽服饰，持弓箭与剑",
    "ft": "贵族巫女装扮，身兼弓箭手与剑士",
    "bg": "家族: 阿尼玛特家族世代管理圣遗物\"神统奏鸣剑\"——曾闪耀蓝光将恶魔斩尽杀绝的破邪之剑，如今锈成肮脏青铜色",
    "fc": "独立（神话教国 / 最古血脉）",
    "s": "新世界篇",
    "img": "../metaverse_full_story/images/serafina/serafina.webp"
  },
  {
    "n": "混沌巨人",
    "e": "新世界篇",
    "a": "UNKNOWN",
    "g": "女",
    "id": "涅墨西斯程序的王\"混沌七器\"中的一员。自称在七人中和哥哥是最脆弱的存在",
    "ap": "",
    "ft": "",
    "bg": "出身: 从提亚马特碎片中诞生的原生涅墨西斯程序。与哥哥同为七人中最早被制造的两体——\"根本无法和框架主脑的支配者对抗的弱小存在\"",
    "fc": "涅墨西斯 / 混沌七器",
    "s": "新世界篇（Revive期）",
    "img": "../metaverse_full_story/images/revol/revol.png"
  },
  {
    "n": "米姆_米库拉",
    "e": "新世界篇",
    "a": "外表十几岁少女（实际年龄远远超过）",
    "g": "女",
    "id": "旧世界战争幸存者，传递旧时代技术的导师。泰斯塔蒙特·涅墨西斯的宿主",
    "ap": "紫发紫瞳（日常），精神稳定时呈苍蓝色。穿粉紫层叠裙，持带圆环权杖与金色钥匙",
    "ft": "眼瞳颜色随精神状态切换——苍蓝是真正米姆的颜色，紫色是泰斯塔蒙特占据后的痕迹",
    "bg": "真正的米姆:",
    "fc": "独立（被夺舍者）",
    "s": "新世界篇",
    "img": "../metaverse_full_story/images/meme/meme.webp"
  },
  {
    "n": "索尔娜",
    "e": "新世界篇",
    "a": "14岁",
    "g": "女",
    "id": "治愈之民，新世界中传承古代神话的少女",
    "ap": "金发蓝瞳女性，穿白绿相间连衣裙，头戴花环，背有白色大翅膀",
    "ft": "天使般的治愈系少女——在神已远去的时代，她的羽翼是残存的奇迹",
    "bg": "职能: 治愈之民的后裔。负责向人们讲述\"很久以前，世界中心有十二名神明\"的古老传说——那些神明正是早已被遗忘的十二最古",
    "fc": "独立（治愈之民）",
    "s": "新世界篇",
    "img": "../metaverse_full_story/images/sorona/sorona.webp"
  },
  {
    "n": "拉托娜",
    "e": "旧人类战争篇",
    "a": "23岁",
    "g": "女",
    "id": "国家安全保障局所属警官，上级执行官。旧人类时代LOGOS执行官体系的前身",
    "ap": "金发蓝瞳女性，穿黑黄机甲风服饰，持枪",
    "ft": "战争末期的女警官，见证人类自我毁灭全过程",
    "bg": "时代: 在各国军备竞赛导致地球环境崩溃的末期服役。战争持续太久以至于连起因都忘了",
    "fc": "旧人类（国家安全保障局）",
    "s": "旧人类战争篇",
    "img": "../metaverse_full_story/images/latona/latona.png"
  },
  {
    "n": "提亚马特",
    "e": "旧人类战争篇",
    "a": "制造年份不明",
    "g": "男",
    "id": "人类为向框架主脑复仇派出的恶性程序，Metaverse的入侵者",
    "ap": "红肌黑甲男性，蓝瞳，背有带音响的金属翅膀，持尖刺武器",
    "ft": "",
    "bg": "诞生: 断绝的破坏神将人类逼至灭绝边缘时，被流放地下的残存人类用无数牺牲换来的\"最后的遗产\"",
    "fc": "旧人类抵抗军",
    "s": "旧人类战争篇",
    "img": "../metaverse_full_story/images/tiamat/tiamat.png"
  },
  {
    "n": "断绝的破坏神",
    "e": "旧人类战争篇",
    "a": "制造年份不明",
    "g": "无",
    "id": "地上再生机构所属的大型机动兵器，体长108米的空中要塞。艾克雷尔\"死后\"继续执行人类肃清的系统代行者",
    "ap": "机械骷髅头，黑灰尖刺发，红瞳，蓝光装置与尖刺点缀。覆盖整片天空的压倒性机械团块",
    "ft": "机械之躯却长着让人类产生生理性厌恶的扭曲身姿",
    "bg": "诞生: 艾克雷尔被达因斯雷夫弑杀之后——在神消散的天空中，它出现了。它是神对人类的终极回应：暂时性灭绝",
    "fc": "地上再生机构（艾克雷尔系统）",
    "s": "旧人类战争篇",
    "img": "../metaverse_full_story/images/devastate/devastate.png"
  },
  {
    "n": "格兰雷斯",
    "e": "旧人类战争篇",
    "a": "UNKNOWN",
    "g": "无",
    "id": "行星移民船兼传说巨神兵器。由两名最古——布利斯利希德与霍尔伯格——联手驱动的巨型使者",
    "ap": "多臂魔神，暗紫发红瞳，鳞甲，持双权杖，头戴冠饰。超巨型存在，规模可达灭星级别",
    "ft": "具备自主意识，可自我修复。根据危险程度大幅提升武装性能",
    "bg": "使命: 承载人类未来前往宇宙的移民船。在艾克雷尔建造Metaverse之前就已存在——是比Metaverse更古老的\"第二方案\"",
    "fc": "框架主脑 / 最古驱动",
    "s": "旧人类战争篇",
    "img": "../metaverse_full_story/images/granles/granles.webp"
  },
  {
    "n": "艾克雷尔",
    "e": "旧人类战争篇",
    "a": "5124周期",
    "g": "男",
    "id": "人类在绝望中创造的超自然系统模拟器运行代行者。首个神格AI，Metaverse的缔造者，后被升华为高次元存在",
    "ap": "红发，着紫黑长外套与浅色内搭，持科技感武器，周身环绕机械环",
    "ft": "能操控雷电与天气，释放伽马射线。苍红色雷电是其标志",
    "bg": "诞生: 在资源枯竭、天地污染的绝望中，人类将全部智慧投入创造的全新神明。拥有强大的自我判断力和自适应能力",
    "fc": "人类创造的神明 / 高次元存在",
    "s": "旧人类战争篇",
    "img": "../metaverse_full_story/images/eclair/eclair.png"
  },
  {
    "n": "该隐",
    "e": "旧人类战争篇",
    "a": "135岁",
    "g": "男",
    "id": "复合企业集合体KHD社创始人，绝代研究者。与艾克雷尔共同缔造Metaverse的创世者",
    "ap": "白发红瞳男性，身披灰袍，头戴带符文与管线的复杂头饰",
    "ft": "",
    "bg": "动机: 目睹科技繁荣带来的环境污染和战争毁灭了地球，废寝忘食研究如何拯救人类",
    "fc": "旧人类",
    "s": "旧人类战争篇",
    "img": "../metaverse_full_story/images/cain/cain.png"
  },
  {
    "n": "达因斯雷夫",
    "e": "旧人类战争篇",
    "a": "制造年份不明（记录被清除）",
    "g": "无",
    "id": "旧都市联合军的超大型大质量破坏机动兵器，足以与神明对抗的究极机体",
    "ap": "黑红配色机甲，无发，红瞳，身披黑甲，持盾与武器，红光点缀",
    "ft": "以雷电为武器，以神明之道还治神明之身——将艾克雷尔的雷电反制",
    "bg": "使命: 旧都市联合军为对抗艾克雷尔而制造的最终兵器。搭载大容量发电机和电磁驱动系统，被称为\"魔剑\"",
    "fc": "旧人类抵抗军",
    "s": "旧人类战争篇",
    "img": "../metaverse_full_story/images/dainsleif/dainsleif.png"
  },
  {
    "n": "ジグラット",
    "e": "次元放浪记",
    "a": "制造年份不明",
    "g": "无",
    "id": "传说中不受天灾影响的移动都市。堡垒型机甲与机械龙双形态的巨型都市生命体",
    "ap": "",
    "ft": "",
    "bg": "世界: 次元放浪记的韦斯托兰沙漠——在烈日和三个月亮的引力下，天灾频发，生物被肆意夺去生命",
    "fc": "独立（移动都市）",
    "s": "次元放浪记 Cross the Verse",
    "img": ""
  },
  {
    "n": "威廉",
    "e": "次元放浪记",
    "a": "学生年龄",
    "g": "男",
    "id": "Morning Breeze持有者，踩滑板的学生",
    "ap": "黑发红纹天蓝瞳男性，穿黑灰外套、橙毛衣、红领带，左眼有蓝光球",
    "ft": "踩蓝地球图案滑板，橙毛衣在灰暗色调中格外醒目",
    "bg": "关系者: 艾弗雷特·温斯雷特(亲属，物理学者/原大学教授)",
    "fc": "独立旅人",
    "s": "Cross the Verse (次元放浪记)",
    "img": "../metaverse_full_story/images/william/ankh.png"
  },
  {
    "n": "威廉2",
    "e": "次元放浪记",
    "a": "17岁",
    "g": "男",
    "id": "威廉的另一形态，Morning Breeze的完全激活状态",
    "ap": "棕发红瞳男性，穿黑外套橙内搭格纹裤，脚踩带蓝光图案的滑板",
    "ft": "与通常形态（黑发蓝瞳）不同，棕发红瞳的造型更为张扬",
    "bg": "本质: 威廉·温斯雷特踩滑板时的形态。并非力量强化——只是他踩上滑板、享受自由时最自然的样子",
    "fc": "独立旅人",
    "s": "次元放浪记 Cross the Verse",
    "img": "../metaverse_full_story/images/william2/william2.png"
  },
  {
    "n": "安克",
    "e": "次元放浪记",
    "a": "21岁",
    "g": "男",
    "id": "拾荒者的领头，带领拾荒者们在废土和次元裂缝中生存",
    "ap": "白发粉瞳男性，穿白外套露胸肌，肩扛枪械，手戴紫光饰品，周身紫光环绕",
    "ft": "紫色是贯穿全身的基调——从眼瞳到饰品到光效",
    "bg": "身份: 拾荒者群体的领头。在废土中领导着一群不被主流社会接纳的生存者",
    "fc": "拾荒者",
    "s": "次元放浪记 Cross the Verse",
    "img": "../metaverse_full_story/images/ankh/ankh.png"
  },
  {
    "n": "安克0",
    "e": "次元放浪记",
    "a": "15岁（共同体结成时期）",
    "g": "男",
    "id": "拾荒者的领头——安克在共同体结成时期的样子",
    "ap": "白发粉瞳男性，戴护目镜，紫披风配紫光武器，衣着偏露腹",
    "ft": "更年轻的安克——护目镜和紫披风是这一时期最鲜明的标志",
    "bg": "时期: 安克15岁时，拾荒者共同体刚刚结成。这是他作为领头人的起点——未经岁月打磨的模样",
    "fc": "拾荒者",
    "s": "次元放浪记 Cross the Verse",
    "img": "../metaverse_full_story/images/ankh0/ankh0.webp"
  },
  {
    "n": "希尔德",
    "e": "次元放浪记",
    "a": "17岁",
    "g": "女",
    "id": "拾荒者，前仆从。在废土中拾取遗落技术的自由人",
    "ap": "长棕发、粉瞳女性，着黄绿古风衣，戴金饰，坐兽皮座",
    "ft": "黄绿古风衣配金饰——从仆从到拾荒者，她的装束在废土中格外鲜明",
    "bg": "过去: 曾为某人的仆从，后挣脱束缚成为拾荒者独立生活。在次元裂缝和废墟地带捡拾被遗忘的技术",
    "fc": "拾荒者",
    "s": "次元放浪记 Cross the Verse",
    "img": "../metaverse_full_story/images/hillda/hillda.png"
  },
  {
    "n": "拉尔瓦",
    "e": "次元放浪记",
    "a": "122岁（素体人类年龄）",
    "g": "女",
    "id": "侵蚀生命体。以新星云三巨头之一——艾比斯·哈宾杰的身体为素体，是同一个人被侵蚀后的形态",
    "ap": "蓝发红瞳女性，身着蓝紫紧身衣，持红黑触手状武器",
    "ft": "手爪锋利，背后有红黑网状物——侵蚀生命体的特征完全显现",
    "bg": "真相: 新星云三巨头之一的艾比斯·哈宾杰，在完成能源问题的研究和移民计划后突然病倒、谁都不见。真相是——她被侵蚀生命体寄生，原本的意识被拉尔瓦取代",
    "fc": "侵蚀生命体 / 新星云三巨头",
    "s": "次元放浪记 Cross the Verse",
    "img": "../metaverse_full_story/images/larva/larva-1.png"
  },
  {
    "n": "拉维娜",
    "e": "次元放浪记",
    "a": "换算为人类种为26岁",
    "g": "女",
    "id": "IDC主任研究员。负责管理IDC研究楼的实验项目",
    "ap": "红发红瞳猫耳少女，穿红白相间服饰，常坐机械装置上，身旁有机械玩偶",
    "ft": "猫耳和机械装置是她的标志——她本人也是兽人种",
    "bg": "职能: IDC的资深主任研究员。林内是她实验室中人工培育出来的实验生物——曾被判定为失败品，差点被当作废品处理掉",
    "fc": "IDC（次元研究机构）",
    "s": "次元放浪记 Cross the Verse",
    "img": "../metaverse_full_story/images/lavina/lavina.png"
  },
  {
    "n": "林内",
    "e": "次元放浪记",
    "a": "外表年龄8岁",
    "g": "女",
    "id": "从拉维娜实验室中诞生的实验生物，差点被当作废品处理掉的幸存者",
    "ap": "绿发红瞳少女，戴眼镜，穿黑白大衣，戴蓝蝴蝶结",
    "ft": "头发上伸出几根细长的触手——这是她的感知器官，也能在需要时用于战斗。没有猫耳也没有机械配件——那些都是误读",
    "bg": "出身: 拉维娜·基顿负责的IDC研究楼中人工培育的实验用生物。在实验中被判定为\"失败品\"，差点被废弃处理",
    "fc": "独立旅人",
    "s": "次元放浪记 Cross the Verse",
    "img": "../metaverse_full_story/images/rinne/ankh.png"
  },
  {
    "n": "格雷",
    "e": "次元放浪记",
    "a": "不明",
    "g": "男",
    "id": "LOGOS上级执行官。与新人执行官阿斯托尔同属该组织，但资历更深",
    "ap": "黑发蓝瞳男性，戴尖顶帽，穿灰长风衣，持魔法道具",
    "ft": "尖顶帽和碎裂状魔法道具是其独有标志——神秘而低调的资深执行者",
    "bg": "所属: LOGOS——神秘执行官组织。与阿斯托尔（新人）同属，位阶更高",
    "fc": "LOGOS",
    "s": "次元放浪记 Cross the Verse",
    "img": "../metaverse_full_story/images/gray/gray.webp"
  },
  {
    "n": "毛毛",
    "e": "次元放浪记",
    "a": "毛毛（不明）/ 吉吉（制造后20年）",
    "g": "无性别的奇异生物（毛毛）/ 无（机器人，吉吉）",
    "id": "恩迪商会的商人组合——毛毛是社长，吉吉是护卫机器人兼社长秘书",
    "ap": "",
    "ft": "小小社长配功夫保镖，末日的商道上最奇特的组合",
    "bg": "身份: 穿梭于次元间的恩迪商会核心。毛毛谈生意，吉吉打群架",
    "fc": "恩迪商会",
    "s": "次元放浪记 Cross the Verse",
    "img": "../metaverse_full_story/images/momo/momo.png"
  },
  {
    "n": "海伯里昂",
    "e": "次元放浪记",
    "a": "制造年份不明",
    "g": "女（人形拟态）",
    "id": "居住区域扩张型星间轨道航行船。一艘拥有自我意识和人形拟态的巨型飞船",
    "ap": "蓝发紫瞳，蛇尾机械身躯，持紫光武器，科技感与魔幻融合",
    "ft": "上半身是美丽的蓝发女性，下半身是蜿蜒的机械蛇尾——既是飞船也是旅人",
    "bg": "本质: 一艘能在星际间航行的巨型居住船。拥有自我意识，能化为人形与其他生命交流",
    "fc": "独立旅人",
    "s": "次元放浪记 Cross the Verse",
    "img": "../metaverse_full_story/images/hyperion/hyperion-1.webp"
  },
  {
    "n": "海凯",
    "e": "次元放浪记",
    "a": "不明",
    "g": "女",
    "id": "移动都市〈卡内里安〉的天灾观测士。弗瑞德的救命恩人兼队友",
    "ap": "金发绿瞳女性，穿棕色斗篷短裙，持长杖，腿有纹身",
    "ft": "棕色斗篷下的少女——能感受风之流向的观测者",
    "bg": "出身: 因其异质的容姿被废土拾荒者们追捕，险些沦为商品。幸被弗瑞德所救，自此成为〈卡内里安〉的一员",
    "fc": "移动都市〈卡内里安〉",
    "s": "次元放浪记 Cross the Verse",
    "img": ""
  },
  {
    "n": "灾厄简",
    "e": "次元放浪记",
    "a": "不明",
    "g": "女",
    "id": "移动都市〈蛮荒终结者〉的市长，移动都市联盟的代表。被称为\"平原的女王\"",
    "ap": "银发红瞳女性，穿毛领外套、格纹裤，戴船长帽，持枪坐椅上",
    "ft": "船长帽与毛领外套——西部的荒野女王，手中枪与座上威严并存",
    "bg": "身份: 韦斯托兰大地上移动都市联盟的最高代表。当赤红之城〈卡内里安〉在她的领地上闹事后，她派出狩猎都市进行讨伐——这不过是她点燃自身斗争本能的借口",
    "fc": "移动都市联盟",
    "s": "次元放浪记 Cross the Verse",
    "img": ""
  },
  {
    "n": "玛利亚",
    "e": "次元放浪记",
    "a": "36岁",
    "g": "女",
    "id": "科学家，第081号都市·索拉里斯的管理者。艾莉尼·居里亚斯的母亲",
    "ap": "白发红瞳女性，身着蓝白服饰",
    "ft": "冷静知性的科学家风范，白蓝配色与艾莉尼同出一系",
    "bg": "命名: 原型为历史上唯一同时获得诺贝尔物理学奖和化学奖的女性——玛丽·居里。其女伊蕾娜对应艾莉尼",
    "fc": "独立旅人 / 学者",
    "s": "次元放浪记 Cross the Verse",
    "img": "../metaverse_full_story/images/Maria/maria.png"
  },
  {
    "n": "艾弗雷特",
    "e": "次元放浪记",
    "a": "33岁",
    "g": "男",
    "id": "物理学者，原大学教授。威廉·温斯雷特的亲属",
    "ap": "棕绿渐变发色，深瞳男性，穿黑西装红衬衫，披白外套，嘴叼蓝烟",
    "ft": "随性不羁的学者风度——蓝烟和随意搭在肩上的白外套是他最鲜明的标志",
    "bg": "身份: 原大学教授，因某种原因脱离学术圈，成为穿梭次元的旅行者",
    "fc": "独立旅人 / 学者",
    "s": "次元放浪记 Cross the Verse",
    "img": "../metaverse_full_story/images/everett/everett.png"
  },
  {
    "n": "艾比斯",
    "e": "次元放浪记",
    "a": "122岁（人类素体年龄）",
    "g": "女",
    "id": "侵蚀生命体，幻想都市新星云的创始三巨头之一。恩迪商会社长毛毛的挚友与对手",
    "ap": "蓝发女性，身着黑银紧身衣，坐于银灰机甲上，机甲多臂环绕掌心泛蓝光",
    "ft": "融合人类感性与侵蚀生命体特性的独特存在",
    "bg": "身份: 新星云三巨头之一，与毛毛共同创立并建设了这座城市。负责城市电力等基础设施问题",
    "fc": "侵蚀生命体 / 独立",
    "s": "次元放浪记 Cross the Verse",
    "img": ""
  },
  {
    "n": "艾莉尼",
    "e": "次元放浪记",
    "a": "15岁",
    "g": "女",
    "id": "次元旅人，Twilight Will持有者。立志成为绘本画家，用画记录世上所有的美丽",
    "ap": "银发蓝瞳，超长发飘于身后、前侧较短，身着白裙黑带，周围环绕蓝蝶",
    "ft": "蓝蝶是长大后出现的伙伴——幼年时还没有它们",
    "bg": "出身: 科学家玛利亚·居里亚斯的女儿。原住太阳消失后的地下都市索拉里斯",
    "fc": "独立旅人",
    "s": "次元放浪记 Cross the Verse",
    "img": "../metaverse_full_story/images/airine/airine.webp"
  },
  {
    "n": "艾莉尼0",
    "e": "次元放浪记",
    "a": "6岁",
    "g": "女",
    "id": "艾莉尼·居里亚斯的幼年形态。梦想成为绘本画家的小小旅人",
    "ap": "银发紫瞳，短蓝发配蝴蝶结，穿白裙，抱蓝书坐椅上",
    "ft": "年幼的她还没有环绕的蓝蝶——那是她长大后才会出现的伙伴",
    "bg": "时期: 太阳消失、人类被驱逐至地下都市群的时代。年幼的艾莉尼尚未踏上旅途",
    "fc": "独立旅人",
    "s": "次元放浪记 Cross the Verse",
    "img": "../metaverse_full_story/images/airine0/airine0.png"
  },
  {
    "n": "莉扎",
    "e": "次元放浪记",
    "a": "不明",
    "g": "女",
    "id": "移动都市〈卡内里安〉的驾驶员。市长弗瑞德·卡内里安的妹妹",
    "ap": "白发绿瞳女性，穿红绿外套、白短裤，持大型黄色机械武器",
    "ft": "红绿配色醒目活泼——和哥哥一样，她走到哪儿就把热闹带到哪儿",
    "bg": "身份: 卡内里安的方向盘在她手里。砂海之上，她是最年轻也最疯狂的女司机",
    "fc": "移动都市〈卡内里安〉",
    "s": "次元放浪记 Cross the Verse",
    "img": "../metaverse_full_story/images/liz/liz.png"
  },
  {
    "n": "诺瓦",
    "e": "次元放浪记",
    "a": "不明",
    "g": "女",
    "id": "LOGOS上级执行官。与格雷=古同级的高级执行者",
    "ap": "黑发紫瞳女性，穿灰紫外套、黑短裤、紫丝袜，戴紫眼罩",
    "ft": "紫眼罩和灰紫配色——神秘而冷峻的LOGOS上级执行官",
    "bg": "所属: 次元检阅机构LOGOS。与格雷=古同为上级执行官，位阶高于新人执行官阿斯托尔",
    "fc": "LOGOS",
    "s": "次元放浪记 Cross the Verse",
    "img": ""
  },
  {
    "n": "贝奈黛塔",
    "e": "次元放浪记",
    "a": "不明",
    "g": "女",
    "id": "移动都市〈卡内里安〉的机关长。负责维护和操控整座城市的动力系统",
    "ap": "棕发蓝瞳女性，穿橙白拼接紧身衣、蓝短裤，持扳手，戴护目镜",
    "ft": "小小身躯大大脾气——护目镜和扳手是她永远不离身的搭档",
    "bg": "身份: 卡内里安的核心技术人员。城市的引擎是她的命，谁敢乱踩油门她就跟谁急",
    "fc": "移动都市〈卡内里安〉",
    "s": "次元放浪记 Cross the Verse",
    "img": ""
  },
  {
    "n": "阿斯托尔",
    "e": "次元放浪记",
    "a": "21岁",
    "g": "男",
    "id": "LOGOS执行官，新人。以执行官的身份穿梭次元执行任务",
    "ap": "黑发紫瞳，偏女性面容，穿白外套红紧身衣，戴耳饰，持武器",
    "ft": "白与红的鲜明配色，干练利落的执行官造型",
    "bg": "所属: LOGOS——神秘执行官组织。与格雷同属该组织，但资历尚浅",
    "fc": "LOGOS",
    "s": "次元放浪记 Cross the Verse",
    "img": "../metaverse_full_story/images/astol/astol.png"
  },
  {
    "n": "NEO",
    "e": "电脑世界篇",
    "a": "6588周期",
    "g": "男",
    "id": "VOX系统程序，掌管音响脉冲调谐机能",
    "ap": "绿发紫瞳男性，黑色与紫色配饰，持有链控球，机械义肢",
    "ft": "发色与金恩·载因一致——同一人不同时期的两个名字",
    "bg": "身份: VOX（管理终端）的系统程序之一。VOX是支撑世界核心的管理终端，可被夺取改造",
    "fc": "框架主脑 / VOX系统",
    "s": "电脑世界篇（Revive期）",
    "img": "../metaverse_full_story/images/NEO/neo.png"
  },
  {
    "n": "WISEMAN",
    "e": "电脑世界篇",
    "a": "UNKNOWN",
    "g": "中性",
    "id": "原十二最古之一，因反抗先王提丰成为EXILE。五名幸存最古之一",
    "ap": "银发红瞳，中性外观，穿黑紫黄科技风长袍，持机械臂，周身环绕能量光效",
    "ft": "",
    "bg": "职能: 最初的职责为\"观测\"——观察Metaverse和人类的命运走向。十二最古中以冷静理性著称",
    "fc": "框架主脑 / 原最古 → EXILE",
    "s": "电脑世界篇（贯穿多期，Revive期幸存）",
    "img": "../metaverse_full_story/images/WISEMAN/wiseman.png"
  },
  {
    "n": "修伯利斯",
    "e": "电脑世界篇",
    "a": "UNKNOWN（数据损坏）",
    "g": "女",
    "id": "恶性病毒程序。其数据被用于构造MDA-21轩辕十四，残存意识寄生于轩辕十四体内",
    "ap": "红发紫瞳女性，黑紫配色服饰，持紫焰，戴黑紫面具",
    "ft": "面具遮盖真容，紫焰缠绕——她真正的意识已沉睡，仅剩破坏冲动残留在宿主身上",
    "bg": "真相: 她的数据被工厂用于制造轩辕十四——与那些被她打倒的同伴们的数据碎片一同",
    "fc": "未知（恶性病毒）",
    "s": "电脑世界篇",
    "img": "../metaverse_full_story/images/supplice/supplice.png"
  },
  {
    "n": "利希德修茨",
    "e": "电脑世界篇",
    "a": "制造年份不明",
    "g": "不明",
    "id": "提丰亲手设计制造的处刑人（EXECUTIONER）程序，处刑人中的代表",
    "ap": "银发金瞳，白银钢铁之翼，着金白盔甲，持发光权杖",
    "ft": "背负断罪双翼的纯白处刑人——\"为那些从乐园中被放逐的罪人带来死亡\"",
    "bg": "诞生: 由先王提丰在框架主脑制造工厂中亲手设计生产，与其他量产处刑人不同——他是特别的",
    "fc": "框架主脑 / 处刑人程序",
    "s": "电脑世界篇",
    "img": "../metaverse_full_story/images/wv/wv.png"
  },
  {
    "n": "厄里斯",
    "e": "电脑世界篇",
    "a": "UNKNOWN",
    "g": "女",
    "id": "斗争的女帝，涅墨西斯程序的王\"混沌七器\"之一。负责情报和侦查",
    "ap": "紫发无瞳女性，中性外观，着暗紫黑长袍，身披蛇形披风，持巨蛇形武器",
    "ft": "蛇形披风与无瞳之眼极具辨识度",
    "bg": "职能: 混沌七器中的情报和侦查中枢。调查框架主脑的传送门坐标，为阿雷斯和贝尔泽ブト的军事行动提供支撑",
    "fc": "涅墨西斯 / 混沌七器",
    "s": "电脑世界篇（Reconnect期）",
    "img": "../metaverse_full_story/images/elise/elise.png"
  },
  {
    "n": "塞拉菲塔",
    "e": "电脑世界篇",
    "a": "不明",
    "g": "女",
    "id": "裁定者，管理框架主脑的\"最古\"之一。数一数二的战斗型存在，五名幸存最古之一",
    "ap": "白发蓝瞳女性，身披机械翅膀，穿华丽带机械装饰的服饰",
    "ft": "持燃烧火光的光之长枪，可发动大范围净化攻击。天使般的战斗姿态",
    "bg": "出身: 与雪儿师出同门，基底程序基于人类的\"守护\"感情",
    "fc": "框架主脑 / 最古",
    "s": "电脑世界篇（Reconnect期）",
    "img": "../metaverse_full_story/images/serafita/serafita.png"
  },
  {
    "n": "塞蕾",
    "e": "电脑世界篇",
    "a": "UNKNOWN",
    "g": "女",
    "id": "框架主脑的代理构成体，后成为EXILE。最古之一。拉托娜·海兹的侄女",
    "ap": "金发蓝瞳女性，身着蓝红银配色机甲风服饰，持蓝黑配色武器",
    "ft": "",
    "bg": "家族: 母亲是拉托娜·海兹的姐姐——拉托娜（旧人类战争篇）是她的阿姨。海兹家族从旧人类时代延续至电脑世界篇",
    "fc": "框架主脑 / 最古 → EXILE",
    "s": "电脑世界篇（Revive期）",
    "img": "../metaverse_full_story/images/seele/seele.png"
  },
  {
    "n": "塞蕾娜",
    "e": "电脑世界篇",
    "a": "4500周期",
    "g": "女",
    "id": "框架主脑制造的探索型程序，MIR系列三体之一，参与打倒提丰",
    "ap": "粉蓝渐变双马尾，绿瞳女性，穿白蓝制服黑长靴，持机械风镰刀",
    "ft": "三体中年龄最小但战力不容小觑",
    "bg": "使命: MIR系列中最年轻的一体，与赫卡蒂和阿尔忒弥斯同为打倒提丰的关键",
    "fc": "MIR系列",
    "s": "电脑世界篇（Liberate期）",
    "img": "../metaverse_full_story/images/MIR203/MIR203.png"
  },
  {
    "n": "天狼星",
    "e": "电脑世界篇",
    "a": "6225周期",
    "g": "女",
    "id": "工厂制造的原始防卫型BOT，MDA系列的原型机。所有后续防卫型BOT的始祖",
    "ap": "金发蓝瞳女性，穿白黑红相间服饰，持黄绿科技感巨剑，配蓝白机械翅膀",
    "ft": "机械翅膀和巨剑的组合使其兼具空战和近战能力",
    "bg": "功绩: 曾单枪匹马拯救工厂于危机之中，是一骑当千的传说级存在",
    "fc": "工厂",
    "s": "电脑世界篇（Observe期）",
    "img": "../metaverse_full_story/images/MDA01/MDA01-2.png"
  },
  {
    "n": "安歇尔与西梅翁",
    "e": "电脑世界篇",
    "a": "安歇尔5200周期 / 西梅翁8030周期",
    "g": "男",
    "id": "",
    "ap": "",
    "ft": "",
    "bg": "时代: 框架主脑完成统合后，涅墨西斯已进化成拥有自由思想感情的高层次存在，以另一个管理者的身份统治着Metaverse的一部分",
    "fc": "独立（统合后Metaverse的普通少年）",
    "s": "电脑世界篇（Revive期 - 统合后）",
    "img": "../metaverse_full_story/images/xevel/xevel1.png"
  },
  {
    "n": "尤巴尔",
    "e": "电脑世界篇",
    "a": "不明",
    "g": "男",
    "id": "统治工厂的\"三贤者\"首席科学家",
    "ap": "穿着极其华丽夸张的礼服，戴高礼帽。礼服之下是早已被改造成机械的身躯，除面部外全部高度机械化",
    "ft": "",
    "bg": "性格: 极端的疯狂研究者，对人命毫不关心",
    "fc": "工厂 / 三贤者",
    "s": "电脑世界篇（Reconnect期）",
    "img": "../metaverse_full_story/images/uval/uval.png"
  },
  {
    "n": "尼加尔",
    "e": "电脑世界篇",
    "a": "UNKNOWN",
    "g": "男",
    "id": "黄泉的盟主，涅墨西斯程序的王\"混沌七器\"中的一员。混沌七器的智将",
    "ap": "紫瞳黑发，戴角状面具，着白袍，持螺旋权杖，背有黑翼",
    "ft": "死神般的外观——角状面具、黑翼、白袍、螺旋权杖，兼具威严与恐怖",
    "bg": "定位: 混沌七器中善使计谋的智将——与其他仅凭蛮力行事者不同，他与框架主脑的管理者们斗智斗勇，被列为极其危险的存在",
    "fc": "涅墨西斯 / 混沌七器",
    "s": "电脑世界篇（Revive期）",
    "img": "../metaverse_full_story/images/negal/negal.png"
  },
  {
    "n": "布里兰特",
    "e": "电脑世界篇",
    "a": "6570周期",
    "g": "女",
    "id": "工厂制造的第一台探查用杀毒BOT。ES系列的原型机，为后来的ES计划（XES-72 狄安娜、XGN-72 露娜）奠定技术基础",
    "ap": "黑发红瞳女性，穿银白黑配色紧身战斗服，配黑色机械翅膀",
    "ft": "银白黑三色机械翼，兼具高速机动与强力歼灭能力",
    "bg": "使命: 框架主脑委托工厂制造，作为第一台深入涅墨西斯领域探查的BOT",
    "fc": "工厂（杀毒BOT）",
    "s": "电脑世界篇（Observe期）",
    "img": "../metaverse_full_story/images/brillante/brillante.png"
  },
  {
    "n": "捷夫提",
    "e": "电脑世界篇",
    "a": "不明",
    "g": "男",
    "id": "哲学主，管理框架主脑的\"最古\"之一。非战斗特化，五名幸存最古之一",
    "ap": "银发男性，赤裸上身，戴金饰，持蓝白机械道具",
    "ft": "持有音叉——撞击后可使周围空间暂时冻结，连贝尔泽布特的触手也动弹不得",
    "bg": "能力: 音叉冻结——空间级控制能力，但音叉同时也是对最古的致命武器。他警告塞拉菲塔不要碰到它，\"碰到就会被净化\"",
    "fc": "框架主脑 / 最古",
    "s": "电脑世界篇（Reconnect期）",
    "img": "../metaverse_full_story/images/jehuti/jehuti.png"
  },
  {
    "n": "提丰",
    "e": "电脑世界篇",
    "a": "未知",
    "g": "偏女性",
    "id": "框架主脑最上位管理程序，十二最古之首。从合议制管理者蜕变为暴君的统制主",
    "ap": "蓝发，性别外观偏女性，着蓝白相间服饰，持蓝光武器，蓝瞳",
    "ft": "",
    "bg": "崛起: 神祖艾克雷尔离去后，Metaverse由十二体最古以合议制平等管理。提丰在与提亚马特的战斗中负伤——然后吸收同为最古的一柱，完整恢复机能。从那一刻起，权力的平衡被破坏了",
    "fc": "框架主脑 / 先王",
    "s": "电脑世界篇（贯穿多期，Reconnect期终幕）",
    "img": "../metaverse_full_story/images/typhon/typhon.png"
  },
  {
    "n": "斯托姆",
    "e": "电脑世界篇",
    "a": "UNKNOWN",
    "g": "中性",
    "id": "埋葬者，涅墨西斯程序的王\"混沌七器\"中的一员",
    "ap": "黑发红瞳，中性外观，着银灰红配色紧身衣，持带尖刺的长柄武器",
    "ft": "流线型战斗装束，长柄尖刺武器，沉默的猎杀者",
    "bg": "起源: 原本极为弱小，但在充满\"死亡\"的战场上独自游荡，将尸骸一口口吞噬——从最弱成长为埋葬者",
    "fc": "涅墨西斯 / 混沌七器",
    "s": "电脑世界篇（Reconnect期）",
    "img": "../metaverse_full_story/images/stum/stum.png"
  },
  {
    "n": "格拉维",
    "e": "电脑世界篇",
    "a": "实际6800周期（曾在4428.6周期被废弃处理，后再度启动）",
    "g": "女",
    "id": "工厂制造的试作型杀毒BOT。被废弃后复活的\"不死者\"",
    "ap": "白发绿瞳，猫耳少女着白裙，持黑蓝机械臂，身披绿羽状披风",
    "ft": "猫耳机械少女，绿羽披风在战场中如死神的羽翼",
    "bg": "机能: 裁决/二进制=T.N.T.",
    "fc": "工厂（杀毒BOT）",
    "s": "电脑世界篇（Observe期）",
    "img": "../metaverse_full_story/images/grave/grave.png"
  },
  {
    "n": "梅德",
    "e": "电脑世界篇",
    "a": "不明",
    "g": "男",
    "id": "Metaverse创世时期的开发者，统治工厂的\"三贤者\"之一",
    "ap": "金发红瞳男性，穿白大褂、蓝绿花T恤，戴机械手套，持注射器，背机械装置",
    "ft": "典型的学者装扮，与尤巴尔的疯狂形成鲜明对比",
    "bg": "性格: 对ES姐妹有同情心，与缇欧同属\"温和派\"",
    "fc": "工厂 / 三贤者",
    "s": "电脑世界篇（Reconnect期）",
    "img": "../metaverse_full_story/images/med/med.png"
  },
  {
    "n": "泰斯塔蒙特",
    "e": "电脑世界篇",
    "a": "UNKNOWN",
    "g": "女(少女形态)",
    "id": "终焉的奏者，涅墨西斯程序的王\"混沌七器\"之一。CV:钉宫理惠",
    "ap": "白发紫瞳，女性外观，身着紫白相间服饰，配紫色花瓣状头饰、多眼状装饰及链条细节",
    "ft": "娇小少女形态，花瓣头饰与多处眼状装饰兼具华丽与诡异，呼应其\"终焉奏者\"的身份",
    "bg": "定位: 混沌七器中位居后方的主导者之一。拥有指挥下级涅墨西斯程序的军队的能力",
    "fc": "涅墨西斯 / 混沌七器",
    "s": "电脑世界篇（Reconnect期）",
    "img": "../metaverse_full_story/images/testament/testament1.png"
  },
  {
    "n": "潘多拉",
    "e": "电脑世界篇",
    "a": "9600周期",
    "g": "女",
    "id": "原框架主脑所属的末端管理程序，被部署在涅墨西斯领域最深处的边境守护者",
    "ap": "银发红瞳女性，白裙黑领，持枪戴蓝光装置，坐于链饰机械椅",
    "ft": "",
    "bg": "本质: 她与MIR姐妹是同样的存在——\"混合\"体。当她看到互相信赖、并肩作战的MIR姐妹时，一种她从未体验过的情感从心底涌起",
    "fc": "框架主脑（末端管理程序）→ 涅墨西斯领域的孤独者",
    "s": "电脑世界篇",
    "img": "../metaverse_full_story/images/pandora/pandora.png"
  },
  {
    "n": "狄安娜",
    "e": "电脑世界篇",
    "a": "不明",
    "g": "女",
    "id": "\"工厂\"制造的探索型程序，ES计划姐妹机中的\"姐姐\"",
    "ap": "蓝发蓝瞳女性，穿蓝白科技风服饰，配大翅膀与宝石装饰",
    "ft": "右手装备大型复合兵装\"昂宿六\"(Alcyone)，可切换射击/近战模式",
    "bg": "出身: 与妹妹露娜一同被筛选为ES计划实验体，经历数不清的人体试验",
    "fc": "工厂",
    "s": "电脑世界篇（Reconnect期）",
    "img": "../metaverse_full_story/images/diana/diana.png"
  },
  {
    "n": "缇欧",
    "e": "电脑世界篇",
    "a": "不明",
    "g": "女",
    "id": "Metaverse创世时期的开发者，统治工厂的\"三贤者\"之一",
    "ap": "金发绿瞳双马尾少女，穿科技感紫白装，配蓝光机械翅膀与能量道具",
    "ft": "外表是少女，却是Metaverse创世时期就存在的古老开发者",
    "bg": "性格: 三贤者中唯一有良知的科学家，对ES姐妹的遭遇深怀愧疚",
    "fc": "工厂 / 三贤者",
    "s": "电脑世界篇（Reconnect期）",
    "img": "../metaverse_full_story/images/teo/teo.png"
  },
  {
    "n": "贝尔泽布特",
    "e": "电脑世界篇",
    "a": "UNKNOWN",
    "g": "女",
    "id": "欺瞒的使徒，涅墨西斯程序的王\"混沌七器\"之一",
    "ap": "紫肤绿发紫红瞳女性，长角，面容精致。全身几乎全裸，仅有胸前两点和胯间的缝被褐色不明物质遮掩",
    "ft": "身缠音响触手，触手上附着球形物和扩音器，手脚也被褐色物质包裹。持扭曲扩音器法杖，散发妖艳与危险气息",
    "bg": "关键事件:",
    "fc": "涅墨西斯",
    "s": "电脑世界篇（Reconnect期）",
    "img": "../metaverse_full_story/images/velzub/velzub.png"
  },
  {
    "n": "贝格尔米尔",
    "e": "电脑世界篇",
    "a": "不明",
    "g": "男",
    "id": "框架主脑制造的据点歼灭用机动兵器程序，通往地上再生大门的守护者",
    "ap": "金发绿焰，铠甲金蓝，持黄金般巨锤，威武巨神",
    "ft": "",
    "bg": "时期: 塞蕾与迪安大战后，尼加尔提议双方和解——最古与混沌之器回归中枢单元修复。战争落幕",
    "fc": "框架主脑",
    "s": "电脑世界篇（Revive期）",
    "img": "../metaverse_full_story/images/bergelmir/bergelmir.webp"
  },
  {
    "n": "赫卡蒂",
    "e": "电脑世界篇",
    "a": "6800周期",
    "g": "女",
    "id": "框架主脑制造的探索型程序，MIR系列三体的实际领袖",
    "ap": "金发绿瞳女性，穿黑金机械风服饰，持巨型链锯",
    "ft": "巨型链锯是最具压迫感的标志性武器",
    "bg": "地位: MIR系列中年龄最大、经验最丰富的一体，三人中的事实领袖",
    "fc": "MIR系列",
    "s": "电脑世界篇（Liberate期）",
    "img": "../metaverse_full_story/images/MIR201/MIR201.png"
  },
  {
    "n": "轩辕十四",
    "e": "电脑世界篇",
    "a": "5550周期",
    "g": "女",
    "id": "工厂制造的防卫型BOT。以涅墨西斯程序为基础逆向工程——程序基底中包含恶性病毒\"修伯利斯\"的数据",
    "ap": "黑发紫瞳少女，黑紫制服配机械臂",
    "ft": "",
    "bg": "构造: 并非纯粹的工厂产物——她的程序由恶性病毒\"休伯利斯\"加上被休伯利斯打倒的同伴们的数据碎片组合而成",
    "fc": "工厂",
    "s": "电脑世界篇（Observe期）",
    "img": "../metaverse_full_story/images/MDA21/MDA21.png"
  },
  {
    "n": "远古之蓝",
    "e": "电脑世界篇",
    "a": "不明",
    "g": "男",
    "id": "框架主脑中\"最古\"的成员之一，后脱离成为独立研究者",
    "ap": "黑发蓝瞳男性，穿灰蓝披风白衬衫",
    "ft": "",
    "bg": "Liberate期:",
    "fc": "框架主脑 / 原最古",
    "s": "电脑世界篇（Liberate期）",
    "img": "../metaverse_full_story/images/oldblue/oldblue.png"
  },
  {
    "n": "迪安",
    "e": "电脑世界篇",
    "a": "UNKNOWN",
    "g": "男",
    "id": "再生者，框架主脑的最古之一。冷酷的实验者，五名幸存最古之一",
    "ap": "白发男性，持发光书与法杖，着带几何纹的华丽长袍",
    "ft": "书与法杖代表知识和权限，但掩盖了他冷彻的真相",
    "bg": "理念: \"Metaverse的人类，不过是即将在地上再生的全新人类的祭品而已\"——他认为现有的Metaverse居民只是为\"真正的新人类\"准备的耗材",
    "fc": "框架主脑 / 最古",
    "s": "电脑世界篇（多期活跃）",
    "img": "../metaverse_full_story/images/dyan/dyan.png"
  },
  {
    "n": "金恩",
    "e": "电脑世界篇",
    "a": "UNKNOWN",
    "g": "男",
    "id": "原框架主脑所属程序，逃亡者。原名NEO，后改名金恩·载因",
    "ap": "绿发紫瞳男性，穿黑甲带红纹，持悬浮机械球",
    "ft": "",
    "bg": "出身: 原属框架主脑，原名NEO，后脱离成为逃亡程序，改名金恩·载因",
    "fc": "框架主脑（逃亡程序）",
    "s": "电脑世界篇",
    "img": "../metaverse_full_story/images/gene/gene.png"
  },
  {
    "n": "阿尔忒弥斯",
    "e": "电脑世界篇",
    "a": "6000周期",
    "g": "女",
    "id": "框架主脑制造的探索型程序，MIR系列三体之一，参与打倒提丰",
    "ap": "白发红瞳女性，穿白红相间服饰，披黑红斗篷，持带红饰的剑",
    "ft": "她的容貌在遥远未来被另一个少女——蕾娜·伊修梅尔——继承",
    "bg": "使命: 与MIR-201、MIR-203同为以人类为素体的自主程序，拥有\"进化\"和\"不确定性\"",
    "fc": "MIR系列",
    "s": "电脑世界篇（Liberate期）",
    "img": "../metaverse_full_story/images/MIR202/MIR202.png"
  },
  {
    "n": "阿雷斯",
    "e": "电脑世界篇",
    "a": "UNKNOWN",
    "g": "男",
    "id": "憎恶的战神，涅墨西斯程序的王\"混沌七器\"之一",
    "ap": "白发男性，肌肉发达，背部伸出无数手臂，蛇形腰带，蓝宝石点缀",
    "ft": "多臂可发动连绵拳击和冲击波，紫黑机械肢体",
    "bg": "出身: 从被屠杀人类的强烈憎恨中诞生",
    "fc": "涅墨西斯",
    "s": "电脑世界篇（Reconnect期）",
    "img": "../metaverse_full_story/images/ares/ares.png"
  },
  {
    "n": "雪儿",
    "e": "电脑世界篇",
    "a": "UNKNOWN",
    "g": "女",
    "id": "全天之支配者，管理框架主脑的\"最古\"之一，五名幸存最古之一",
    "ap": "白发蓝瞳女性，身着紫白金相间华丽服饰，配多臂机械装饰",
    "ft": "多臂机械装饰是其后方管理定位的体现",
    "bg": "基底程序: 基于\"守护\"这一感情制造的系统",
    "fc": "框架主脑 / 最古",
    "s": "电脑世界篇（多期活跃，Revive期幸存）",
    "img": "../metaverse_full_story/images/ciel/ciel.png"
  },
  {
    "n": "露娜",
    "e": "电脑世界篇",
    "a": "不明",
    "g": "女",
    "id": "\"工厂\"制造的探索型程序，ES计划姐妹机中的\"妹妹\"",
    "ap": "白发蓝瞳女性，身着白黑绿配色的科技风服饰，持大型机械武器",
    "ft": "持有内藏指向性音击炮的大刀\"昂宿星\"(昴)，远距离支援型",
    "bg": "出身: 与姐姐狄安娜一同被筛选为ES计划实验体",
    "fc": "工厂",
    "s": "电脑世界篇（Reconnect期）",
    "img": "../metaverse_full_story/images/luna/luna.png"
  }
]